internet/__init__.py
internet/ipv4/CidrBlock.py
internet/ipv4/IP.py
internet/ipv4/__init__.py
internet/ipv4/_reverse_insort.py
internet/ipv4/ip_to_int.py
internet/ipv4/is_in_block.py
internet/ipv4/is_ipv4.py
internet/wikipedia/InfoBox.py
internet/wikipedia/Page_helpers.py
internet/wikipedia/Wikipedia.py
internet/wikipedia/WikipediaMemory.py
internet/wikipedia/WikipediaPage.py
internet/wikipedia/__init__.py
internet/wikipedia/exceptions.py
internet/wikipedia/get_special_data.py
internet/wikipedia/get_wikipedia_id.py
internet/wikipedia/is_wikipedia_page_url.py
internet-2022.4.20.3.dist-info/LICENSE
internet-2022.4.20.3.dist-info/METADATA
internet-2022.4.20.3.dist-info/WHEEL
internet-2022.4.20.3.dist-info/top_level.txt
internet-2022.4.20.3.dist-info/RECORD
