Metadata-Version: 2.1
Name: internet
Version: 2022.4.20.3
Summary: Python library for working with IP addresses and other internet related functionalities
Home-page: https://github.com/idin/internet
Author: Idin
Author-email: py@idin.ca
License: MIT
Platform: UNKNOWN
Requires-Python: ~=3.6
Requires-Dist: base32hex
Requires-Dist: numpy
Requires-Dist: pandas
Requires-Dist: pyspark
Requires-Dist: disk
Requires-Dist: abstract (>=2022.4.20)
Requires-Dist: pensieve (>=2022.4.20)
Requires-Dist: chronometry
Requires-Dist: requests
Requires-Dist: soupspoon (>=2022.4.20)
